davidpy/__init__.py
davidpy/davidpy.py
DAVIDpy-0.1.1.dist-info/LICENSE
DAVIDpy-0.1.1.dist-info/METADATA
DAVIDpy-0.1.1.dist-info/WHEEL
DAVIDpy-0.1.1.dist-info/entry_points.txt
DAVIDpy-0.1.1.dist-info/top_level.txt
DAVIDpy-0.1.1.dist-info/RECORD
