Metadata-Version: 2.1
Name: DAVIDpy
Version: 0.1.1
Summary: Python3 extension for DAVID Bioinformatics Tool
Home-page: https://github.com/narek01/DAVIDpy
Author: Narek Engibaryan
Author-email: narek030601@yandex.ru
License: GPLv3
Platform: UNKNOWN
Classifier: License :: OSI Approved :: GNU General Public License v3 (GPLv3)
Classifier: Topic :: Scientific/Engineering
Classifier: Topic :: Scientific/Engineering :: Bio-Informatics
Requires-Dist: pandas (>=1.0.0)
Requires-Dist: suds (>=0.4)
Requires-Dist: biomart
